<?xml version="1.0" encoding="UTF-8"?>
<objects serializationModel="Studio.02.02.00">
	<object class="AudioFile" id="{1b8e1a9b-c1e9-4ccb-a2ec-3f8abdc6b392}">
		<property name="assetPath">
			<value>SFX/Footsteps - Essentials/Footsteps_Tile/Footsteps_Tile_Walk/Footsteps_Tile_Walk_03.wav</value>
		</property>
		<property name="frequencyInKHz">
			<value>48</value>
		</property>
		<property name="channelCount">
			<value>1</value>
		</property>
		<property name="length">
			<value>0.53477083333333331</value>
		</property>
		<relationship name="masterAssetFolder">
			<destination>{85914e7c-d39d-497b-bfb8-24539c437bae}</destination>
		</relationship>
	</object>
</objects>
